web_explorer_mcp/__init__.py
web_explorer_mcp/business/__init__.py
web_explorer_mcp/business/interfaces.py
web_explorer_mcp/business/services.py
web_explorer_mcp/config/__init__.py
web_explorer_mcp/config/logging_config.py
web_explorer_mcp/config/settings.py
web_explorer_mcp/entrypoints/__init__.py
web_explorer_mcp/entrypoints/mcp/__init__.py
web_explorer_mcp/entrypoints/mcp/dependencies.py
web_explorer_mcp/entrypoints/mcp/server.py
web_explorer_mcp/integrations/__init__.py
web_explorer_mcp/integrations/web/__init__.py
web_explorer_mcp/integrations/web/playwright_content_service.py
web_explorer_mcp/integrations/web/searxng_search_service.py
web_explorer_mcp/models/__init__.py
web_explorer_mcp/models/entities.py
web_explorer_mcp-0.3.0.dist-info/WHEEL
web_explorer_mcp-0.3.0.dist-info/entry_points.txt
web_explorer_mcp-0.3.0.dist-info/METADATA
web_explorer_mcp-0.3.0.dist-info/RECORD
