Metadata-Version: 2.3
Name: web-explorer-mcp
Version: 0.3.0
Summary: MCP server for web search and content extraction using SearxNG
Keywords: mcp,model-context-protocol,search,searxng,web-scraping,ai,llm
Author: Sergei Konovalov
Author-email: Sergei Konovalov <l0kifs91@gmail.com>
Classifier: Development Status :: 4 - Beta
Classifier: Intended Audience :: Developers
Classifier: License :: OSI Approved :: MIT License
Classifier: Programming Language :: Python :: 3
Classifier: Programming Language :: Python :: 3.12
Classifier: Topic :: Software Development :: Libraries :: Python Modules
Classifier: Topic :: Internet :: WWW/HTTP :: Indexing/Search
Requires-Dist: pydantic>=2.11.7
Requires-Dist: pydantic-settings>=2.11.0
Requires-Dist: loguru>=0.7.0
Requires-Dist: typer>=0.19.0
Requires-Dist: rich>=14.1.0
Requires-Dist: httpx>=0.28.1
Requires-Dist: fastmcp>=2.12.1
Requires-Dist: beautifulsoup4>=4.13.5
Requires-Dist: lxml>=6.0.1
Requires-Dist: playwright>=1.40.0
Requires-Python: >=3.12
Project-URL: Repository, https://github.com/l0kifs/web-explorer-mcp
